directory_ch_client/__init__.py
directory_ch_client/client.py
directory_ch_client/company.py
directory_ch_client-4.0.3.dist-info/licenses/LICENSE
directory_ch_client-4.0.3.dist-info/METADATA
directory_ch_client-4.0.3.dist-info/WHEEL
directory_ch_client-4.0.3.dist-info/top_level.txt
directory_ch_client-4.0.3.dist-info/RECORD
