Metadata-Version: 2.4
Name: directory_ch_client
Version: 4.0.3
Summary: Python API client for Export Directory Companies House.
Home-page: https://github.com/uktrade/directory-companies-house-search-client
Author: Department for Business and Trade
License: MIT
Classifier: Development Status :: 5 - Production/Stable
Classifier: Environment :: Web Environment
Classifier: Framework :: Django
Classifier: Framework :: Django :: 4.2
Classifier: Intended Audience :: Developers
Classifier: License :: OSI Approved :: MIT License
Classifier: Natural Language :: English
Classifier: Operating System :: OS Independent
Classifier: Programming Language :: Python :: 3.5
Classifier: Programming Language :: Python :: 3.6
Classifier: Programming Language :: Python :: 3.9
Classifier: Programming Language :: Python :: 3.13
Classifier: Programming Language :: Python :: Implementation :: PyPy
Classifier: Topic :: Software Development :: Libraries :: Python Modules
License-File: LICENSE
Requires-Dist: django<5.0,>=4.2.10
Requires-Dist: requests<3.0.0,>=2.18.4
Requires-Dist: monotonic<3.0,>=1.2
Requires-Dist: directory_client_core<8.0.0,>=7.2.12
Provides-Extra: test
Requires-Dist: pytest; extra == "test"
Requires-Dist: pytest-cov; extra == "test"
Requires-Dist: pytest-codecov; extra == "test"
Requires-Dist: GitPython; extra == "test"
Requires-Dist: flake8==5.0.4; extra == "test"
Requires-Dist: requests_mock==1.1.0; extra == "test"
Requires-Dist: twine; extra == "test"
Requires-Dist: wheel<1.0.0,>=0.31.0; extra == "test"
Requires-Dist: setuptools; extra == "test"
Dynamic: author
Dynamic: classifier
Dynamic: description
Dynamic: description-content-type
Dynamic: home-page
Dynamic: license
Dynamic: license-file
Dynamic: provides-extra
Dynamic: requires-dist
Dynamic: summary
